overreact/__init__.py
overreact/_cli.py
overreact/_constants.py
overreact/_datasets.py
overreact/_misc.py
overreact/api.py
overreact/coords.py
overreact/core.py
overreact/io.py
overreact/rates.py
overreact/simulate.py
overreact/thermo/__init__.py
overreact/thermo/_gas.py
overreact/thermo/_solv.py
overreact/tunnel.py
overreact-1.2.0.dist-info/WHEEL
overreact-1.2.0.dist-info/LICENSE
overreact-1.2.0.dist-info/METADATA
overreact-1.2.0.dist-info/entry_points.txt
overreact-1.2.0.dist-info/RECORD
