Metadata-Version: 2.1
Name: overreact
Version: 1.2.0
Summary: ⚛️📈 Create and analyze chemical microkinetic models built from computational chemistry data
Home-page: https://geem-lab.github.io/overreact-guide/
License: MIT
Keywords: chemical-kinetics,computational-chemistry,microkinetics,reactions,thermochemistry
Author: Felipe S. S. Schneider
Author-email: schneider.felipe@posgrad.ufsc.br
Requires-Python: >=3.8,<3.11
Classifier: Development Status :: 4 - Beta
Classifier: Environment :: Console
Classifier: Intended Audience :: Developers
Classifier: Intended Audience :: Education
Classifier: Intended Audience :: Science/Research
Classifier: License :: OSI Approved :: MIT License
Classifier: Operating System :: OS Independent
Classifier: Programming Language :: Python :: 3
Classifier: Programming Language :: Python :: 3.8
Classifier: Programming Language :: Python :: 3.9
Classifier: Programming Language :: Python :: 3.10
Classifier: Topic :: Education
Classifier: Topic :: Scientific/Engineering :: Atmospheric Science
Classifier: Topic :: Scientific/Engineering :: Chemistry
Classifier: Topic :: Software Development :: Libraries :: Python Modules
Provides-Extra: cli
Provides-Extra: fast
Provides-Extra: solvents
Requires-Dist: cclib (>=1,<2)
Requires-Dist: jax (>=0.4,<0.5) ; extra == "fast"
Requires-Dist: jaxlib (>=0.4,<0.5) ; extra == "fast"
Requires-Dist: rich (>=13,<14) ; extra == "cli"
Requires-Dist: scipy (>=1.10,<2.0)
Requires-Dist: thermo (>=0.2,<0.3) ; extra == "solvents"
Project-URL: API documentation, https://geem-lab.github.io/overreact/
Project-URL: Bug Tracker, https://github.com/geem-lab/overreact/issues
Project-URL: Citation, https://doi.org/10.1002/jcc.26861
Project-URL: Documentation, https://geem-lab.github.io/overreact-guide/
Project-URL: Discussions, https://github.com/geem-lab/overreact/discussions
Project-URL: PyPI, https://pypi.org/project/overreact/
Project-URL: Repository, https://github.com/geem-lab/overreact
